django_ltfi_wsap/__init__.py
django_ltfi_wsap/admin.py
django_ltfi_wsap/apps.py
django_ltfi_wsap/forms.py
django_ltfi_wsap/middleware.py
django_ltfi_wsap/models.py
django_ltfi_wsap/serializers.py
django_ltfi_wsap/urls.py
django_ltfi_wsap/views.py
django_ltfi_wsap/management/__init__.py
django_ltfi_wsap/management/commands/__init__.py
django_ltfi_wsap/management/commands/wsap_verify.py
django_ltfi_wsap-2.0.0.dist-info/licenses/LICENSE
django_ltfi_wsap-2.0.0.dist-info/licenses/NOTICE
django_ltfi_wsap-2.0.0.dist-info/METADATA
django_ltfi_wsap-2.0.0.dist-info/WHEEL
django_ltfi_wsap-2.0.0.dist-info/top_level.txt
django_ltfi_wsap-2.0.0.dist-info/RECORD
