Metadata-Version: 2.4
Name: django-ltfi-wsap
Version: 2.0.0
Summary: Django integration for LTFI-WSAP (Layered Transformer Framework Intelligence - Web System Alignment Protocol) by Kief Studio
Home-page: https://github.com/KiefStudioMA/ltfi-wsap-django
Author: Kief Studio
Author-email: developers@kief.studio
License: MIT
Project-URL: Documentation, https://wsap-django.readthedocs.io
Project-URL: Bug Reports, https://github.com/KiefStudioMA/wsap-django/issues
Project-URL: Source, https://github.com/KiefStudioMA/wsap-django
Project-URL: Company, https://kief.studio
Project-URL: LTFI Ecosystem, https://ltfi.ai
Project-URL: WSAP Protocol, https://wsap.ltfi.ai
Keywords: django wsap ltfi verification domain security api integration kief-studio
Classifier: Development Status :: 5 - Production/Stable
Classifier: Intended Audience :: Developers
Classifier: Topic :: Software Development :: Libraries :: Python Modules
Classifier: Topic :: Internet :: WWW/HTTP
Classifier: Topic :: Internet :: WWW/HTTP :: Dynamic Content
Classifier: Framework :: Django
Classifier: Framework :: Django :: 3.2
Classifier: Framework :: Django :: 4.0
Classifier: Framework :: Django :: 4.1
Classifier: Framework :: Django :: 4.2
Classifier: Framework :: Django :: 5.0
Classifier: License :: OSI Approved :: MIT License
Classifier: Programming Language :: Python :: 3
Classifier: Programming Language :: Python :: 3.8
Classifier: Programming Language :: Python :: 3.9
Classifier: Programming Language :: Python :: 3.10
Classifier: Programming Language :: Python :: 3.11
Classifier: Programming Language :: Python :: 3.12
Classifier: Operating System :: OS Independent
Requires-Python: >=3.8
License-File: LICENSE
License-File: NOTICE
Requires-Dist: Django>=3.2
Requires-Dist: ltfi-wsap-sdk>=2.0.0
Provides-Extra: dev
Requires-Dist: pytest>=7.0.0; extra == "dev"
Requires-Dist: pytest-django>=4.5.0; extra == "dev"
Requires-Dist: pytest-cov>=4.0.0; extra == "dev"
Requires-Dist: black>=23.0.0; extra == "dev"
Requires-Dist: flake8>=6.0.0; extra == "dev"
Requires-Dist: mypy>=1.0.0; extra == "dev"
Requires-Dist: django-stubs>=4.2.0; extra == "dev"
Dynamic: author
Dynamic: author-email
Dynamic: classifier
Dynamic: description
Dynamic: description-content-type
Dynamic: home-page
Dynamic: keywords
Dynamic: license
Dynamic: license-file
Dynamic: project-url
Dynamic: provides-extra
Dynamic: requires-dist
Dynamic: requires-python
Dynamic: summary
